segmentation_mask_overlay/__init__.py
segmentation_mask_overlay/main.py
segmentation_mask_overlay/utils.py
segmentation_mask_overlay/video.py
segmentation_mask_overlay-0.4.4.dist-info/LICENSE
segmentation_mask_overlay-0.4.4.dist-info/METADATA
segmentation_mask_overlay-0.4.4.dist-info/WHEEL
segmentation_mask_overlay-0.4.4.dist-info/top_level.txt
segmentation_mask_overlay-0.4.4.dist-info/RECORD
