Metadata-Version: 2.1
Name: segmentation-mask-overlay
Version: 0.4.4
Summary: Plotting the segmentation masks has never been so exciting!
Home-page: https://github.com/lobantseff/segmentation-mask-overlay
Author: Artem Lobantsev
Author-email: lobantseff@gmail.com
License: MIT
Classifier: Programming Language :: Python :: 3
Classifier: License :: OSI Approved :: MIT License
Classifier: Operating System :: OS Independent
Requires-Python: >=3.7
License-File: LICENSE
Requires-Dist: matplotlib
Requires-Dist: numpy
Requires-Dist: opencv-python
Requires-Dist: Pillow
